epicosm_pkg/__init__.py
epicosm_pkg/epicosm.py
epicosm_pkg/epicosm_nlp.py
epicosm_pkg/geo_harvester.py
epicosm_pkg/modules/__init__.py
epicosm_pkg/modules/csv2liwc.py
epicosm_pkg/modules/csv2vader.py
epicosm_pkg/modules/df_cleaning_functions.py
epicosm_pkg/modules/env_config.py
epicosm_pkg/modules/epicosm_meta.py
epicosm_pkg/modules/geo_boxes.py
epicosm_pkg/modules/mongo_ops.py
epicosm_pkg/modules/mongodb_config.py
epicosm_pkg/modules/nlp_ops.py
epicosm_pkg/modules/twitter_ops.py
epicosm-0.0.1.dist-info/LICENSE
epicosm-0.0.1.dist-info/METADATA
epicosm-0.0.1.dist-info/WHEEL
epicosm-0.0.1.dist-info/top_level.txt
epicosm-0.0.1.dist-info/RECORD
