Metadata-Version: 2.1
Name: epicosm
Version: 0.0.1
Summary: Epidemiology of Cohort Social Media
Home-page: https://github.com/DynamicGenetics/Epicosm
Author: Alastair Tanner
Author-email: alastair.tanner@bristol.ac.uk
License: UNKNOWN
Platform: UNKNOWN
Classifier: Programming Language :: Python :: 3
Classifier: License :: OSI Approved :: GNU General Public License (GPL)
Classifier: Operating System :: OS Independent
Requires-Python: >=3.6
